calcom_mcp_for_customers/__init__.py
calcom_mcp_for_customers/cli.py
calcom_mcp_for_customers/server.py
calcom_mcp_for_customers-1.7.0.dist-info/METADATA
calcom_mcp_for_customers-1.7.0.dist-info/WHEEL
calcom_mcp_for_customers-1.7.0.dist-info/entry_points.txt
calcom_mcp_for_customers-1.7.0.dist-info/licenses/LICENSE
calcom_mcp_for_customers-1.7.0.dist-info/RECORD
