Metadata-Version: 2.4
Name: calcom-mcp-for-customers
Version: 1.7.0
Summary: Cal.com MCP server for interacting with the Cal.com API
Project-URL: Repository, https://github.com/Niopub/calcom-mcp-for-customers
Author-email: Founder DS <founder@niopub.com>
License-File: LICENSE
Keywords: api,cal.com,mcp,python,scheduling
Classifier: Intended Audience :: Developers
Classifier: Programming Language :: Python
Classifier: Programming Language :: Python :: 3
Classifier: Programming Language :: Python :: 3.10
Classifier: Programming Language :: Python :: 3.11
Classifier: Programming Language :: Python :: 3.12
Classifier: Topic :: Software Development :: Libraries :: Python Modules
Requires-Python: <4.0,>=3.10
Requires-Dist: fastmcp>=0.1.0
Requires-Dist: pydantic>=2.11.4
Requires-Dist: python-dotenv>=1.0.0
Requires-Dist: pytz>=2025.2
Requires-Dist: requests>=2.31.0
Requires-Dist: typer>=0.15.3
